astrocalc/.DS_Store
astrocalc/.coverage
astrocalc/CHANGES.md
astrocalc/__init__.py
astrocalc/__version__.py
astrocalc/cl_utils.py
astrocalc/default_settings.yaml
astrocalc/docstring_test.py
astrocalc/test_settings.yaml
astrocalc/utKit.py
astrocalc/commonutils/__init__.py
astrocalc/commonutils/getpackagepath.py
astrocalc/coords/__init__.py
astrocalc/coords/coordinates_to_array.py
astrocalc/coords/separations.py
astrocalc/coords/translate.py
astrocalc/coords/unit_conversion.py
astrocalc/coords/tests/test_coordinates_to_array.py
astrocalc/coords/tests/test_separations.py
astrocalc/coords/tests/test_translate.py
astrocalc/coords/tests/test_unit_conversion.py
astrocalc/coords/tests/input/example_settings.yaml
astrocalc/coords/tests/output/example_settings.yaml
astrocalc/distances/__init__.py
astrocalc/distances/converter.py
astrocalc/distances/tests/test_converter.py
astrocalc/distances/tests/input/.gitkeep
astrocalc/distances/tests/output/.gitkeep
astrocalc/resources/package.mplstyle
astrocalc/tests/test_cl_utils.py
astrocalc/tests/input/.gitkeep
astrocalc/tests/output/.gitkeep
astrocalc/times/__init__.py
astrocalc/times/conversions.py
astrocalc/times/now.py
astrocalc/times/tests/test_conversions.py
astrocalc/times/tests/test_now.py
astrocalc/times/tests/input/.gitkeep
astrocalc/times/tests/output/.gitkeep
astrocalc-0.4.6.dist-info/LICENSE
astrocalc-0.4.6.dist-info/METADATA
astrocalc-0.4.6.dist-info/WHEEL
astrocalc-0.4.6.dist-info/entry_points.txt
astrocalc-0.4.6.dist-info/top_level.txt
astrocalc-0.4.6.dist-info/RECORD
