Metadata-Version: 2.2
Name: astrocalc
Version: 0.4.6
Summary: perform common astronomy-related calculations, conversions and measurements within python scripts or from the command-line
Home-page: https://github.com/thespacedoctor/astrocalc
Download-URL: https://github.com/thespacedoctor/astrocalc/archive/v0.4.6.zip
Author: David Young
Author-email: davidrobertyoung@gmail.com
License: MIT
Keywords: astronomy, calculate, convert
Classifier: Development Status :: 4 - Beta
Classifier: License :: OSI Approved :: MIT License
Classifier: Programming Language :: Python :: 3.13
Classifier: Topic :: Utilities
License-File: LICENSE
Requires-Dist: pyyaml
Requires-Dist: numpy
Requires-Dist: scipy
Requires-Dist: fundamentals
Dynamic: author
Dynamic: author-email
Dynamic: classifier
Dynamic: description
Dynamic: description-content-type
Dynamic: download-url
Dynamic: home-page
Dynamic: keywords
Dynamic: license
Dynamic: requires-dist
Dynamic: summary
